lambda_response_utils/__init__.py
lambda_response_utils/encoders.py
lambda_response_utils/exceptions.py
lambda_response_utils/helpers.py
lambda_response_utils/response.py
lambda_response_utils/status.py
lambda_request_response-1.0.0.dist-info/METADATA
lambda_request_response-1.0.0.dist-info/WHEEL
lambda_request_response-1.0.0.dist-info/top_level.txt
lambda_request_response-1.0.0.dist-info/RECORD
